su2gui/__init__.py
su2gui/boundaries.py
su2gui/cfg2json.py
su2gui/fileio.py
su2gui/initialization.py
su2gui/materials.py
su2gui/mesh.py
su2gui/monitor.py
su2gui/numerics.py
su2gui/physics.py
su2gui/pipeline.py
su2gui/solver.py
su2gui/su2_io.py
su2gui/su2_json.py
su2gui/su2gui.py
su2gui/uicard.py
su2gui/vtk_helper.py
su2gui/icons/abacus.svg
su2gui/icons/chevron-down.svg
su2gui/icons/chevron-up.svg
su2gui/icons/trash-can-outline.svg
su2gui/icons/unfold-less-horizontal.svg
su2gui/img/logoSU2small.png
su2gui/img/material.jpg
su2gui/img/overview_su2gui.png
su2gui/user/config.json
su2gui/user/config_new.cfg
su2gui/user/config_new.json
su2gui/user/config_old.json
su2gui/user/cube.cfg
su2gui/user/history.csv
su2gui/user/restart.csv
su2gui/user/restart.dat
su2gui/user/solution.csv
su2guitest-0.0.1.dist-info/LICENSE
su2guitest-0.0.1.dist-info/METADATA
su2guitest-0.0.1.dist-info/WHEEL
su2guitest-0.0.1.dist-info/entry_points.txt
su2guitest-0.0.1.dist-info/top_level.txt
su2guitest-0.0.1.dist-info/RECORD
