Metadata-Version: 2.1
Name: su2guitest
Version: 0.0.1
License-File: LICENSE
Requires-Dist: jsonschema >=4.19.1
Requires-Dist: pandas >=2.1.0
Requires-Dist: setuptools
Requires-Dist: trame >=3.2.0
Requires-Dist: trame-client >=2.12.0
Requires-Dist: trame-components >=2.2.0
Requires-Dist: trame-markdown >=3.0.0
Requires-Dist: trame-matplotlib >=2.0.0
Requires-Dist: trame-server >=2.12.0
Requires-Dist: trame-vtk >=2.5.0
Requires-Dist: trame-vuetify >=2.3.0
Requires-Dist: vtk >=9.2.0
